grai_source_mssql/__init__.py
grai_source_mssql/adapters.py
grai_source_mssql/base.py
grai_source_mssql/loader.py
grai_source_mssql/models.py
grai_source_mssql/package_definitions.py
grai_source_mssql2-0.0.2a6.dist-info/WHEEL
grai_source_mssql2-0.0.2a6.dist-info/METADATA
grai_source_mssql2-0.0.2a6.dist-info/RECORD
